[{"id": "CH-001319-0.Obj.RCH_1134", "thumbnail": "/thumbnails/CH-001319-0.Obj.RCH_1134.jpg", "title": "Das Lied vom Grossen Lande Wu", "artist": "Lu Zhi"}, {"id": "CH-001319-0.Obj.RCH_1235", "thumbnail": "/thumbnails/CH-001319-0.Obj.RCH_1235.jpg", "title": "Pflaumenbl\u00fcten und Bambus im Schnee", "artist": "Kaisermutter Cixi"}, {"id": "CH-001319-0.Obj.RCH_1019", "thumbnail": "/thumbnails/CH-001319-0.Obj.RCH_1019.jpg", "title": "Xiao Yi verschafft sich die Lanting-Rolle durch einen Trick", "artist": "Zhao Lin"}, {"id": "CH-001319-0.Obj.RCH_1152", "thumbnail": "/thumbnails/CH-001319-0.Obj.RCH_1152.jpg", "title": "Landschaft", "artist": "Bian Wenyu"}, {"id": "CH-001319-0.Obj.RCH_1234", "thumbnail": "/thumbnails/CH-001319-0.Obj.RCH_1234.jpg", "title": "Sittich auf einem Ast", "artist": "Hua Yan"}, {"id": "CH-001319-0.Obj.RCH_1170d", "thumbnail": "/thumbnails/CH-001319-0.Obj.RCH_1170d.jpg", "title": "Abendstimmung am Jadefluss\r\nBlatt aus dem Album: Die wunderbaren Ansichten von Xuancheng", "artist": "Mei Qing"}, {"id": "CH-001319-0.Obj.RCH_1181", "thumbnail": "/thumbnails/CH-001319-0.Obj.RCH_1181.jpg", "title": "Landschaft", "artist": "Wang Jian"}, {"id": "CH-001319-0.Obj.RCH_1157", "thumbnail": "/thumbnails/CH-001319-0.Obj.RCH_1157.jpg", "title": "Landschaft", "artist": "Wang Hui"}, {"id": "CH-001319-0.Obj.RCH_1173", "thumbnail": "/thumbnails/CH-001319-0.Obj.RCH_1173.jpg", "title": "Fisch, Ente und Fels", "artist": "Bada shanren / Zhu Da"}, {"id": "CH-001319-0.Obj.RCH_1170a", "thumbnail": "/thumbnails/CH-001319-0.Obj.RCH_1170a.jpg", "title": "Das St\u00e4dtchen Shuiyang\r\nBlatt aus dem Album: Die wunderbaren Ansichten von Xuancheng", "artist": "Mei Qing"}, {"id": "CH-001319-0.Obj.RCH_1174", "thumbnail": "/thumbnails/CH-001319-0.Obj.RCH_1174.jpg", "title": "Tao Yuanmings Heimkehr", "artist": "Dao Ji / Shitao (Zhu Ruoji, Yuanji)"}, {"id": "CH-001319-0.Obj.RCH_1161", "thumbnail": "/thumbnails/CH-001319-0.Obj.RCH_1161.jpg", "title": "Landschaft", "artist": "Huang Ding"}, {"id": "CH-001319-0.Obj.RCH_1146", "thumbnail": "/thumbnails/CH-001319-0.Obj.RCH_1146.jpg", "title": "Herbstwinde", "artist": "Xiang Shengmo"}, {"id": "CH-001319-0.Obj.RCH_1167", "thumbnail": "/thumbnails/CH-001319-0.Obj.RCH_1167.jpg", "title": "Nach Hause zur\u00fcckkehren oder in der Fremde wohnen ist einerlei", "artist": "Xiao Yuncong"}, {"id": "CH-001319-0.Obj.RCH_1171", "thumbnail": "/thumbnails/CH-001319-0.Obj.RCH_1171.jpg", "title": "Einsames Haus in sumpfiger Flusslandschaft", "artist": "Kuncan"}, {"id": "CH-001319-0.Obj.RCH_1170c", "thumbnail": "/thumbnails/CH-001319-0.Obj.RCH_1170c.jpg", "title": "Herbstregen beim Pavillon am See\r\nBlatt aus dem Album: Die wunderbaren Ansichten von Xuancheng", "artist": "Mei Qing"}, {"id": "CH-001319-0.Obj.RCH_1232", "thumbnail": "/thumbnails/CH-001319-0.Obj.RCH_1232.jpg", "title": "Zwei K\u00fcken", "artist": ""}, {"id": "CH-001319-0.Obj.RCH_1169", "thumbnail": "/thumbnails/CH-001319-0.Obj.RCH_1169.jpg", "title": "Gelehrter beim Betrachten eines Wasserfalls", "artist": "Yao Song"}, {"id": "CH-001319-0.Obj.RCH_1132", "thumbnail": "/thumbnails/CH-001319-0.Obj.RCH_1132.jpg", "title": "R\u00fcckkehr von einem Ausflug in die Westberge", "artist": "Wen Zhengming "}, {"id": "CH-001319-0.Obj.RCH_1162a", "thumbnail": "/thumbnails/CH-001319-0.Obj.RCH_1162a.jpg", "title": "Kleiner Pavillon am Wasser\r\nAus dem Album: Landschaften im Stil von Song- und Yuan-Meistern", "artist": "Zhang Zongcang"}, {"id": "CH-001319-0.Obj.RCH_1170q", "thumbnail": "/thumbnails/CH-001319-0.Obj.RCH_1170q.jpg", "title": "Der Schildkr\u00f6ten-Gipfel in den Lingyang-Bergen\nBlatt aus dem Album: Die wunderbaren Ansichten von Xuancheng", "artist": "Mei Qing"}, {"id": "CH-001319-0.Obj.RCH_1170f", "thumbnail": "/thumbnails/CH-001319-0.Obj.RCH_1170f.jpg", "title": "Gelehrtes Gespr\u00e4ch am Echo-Weiher\r\nBlatt aus dem Album: Die wunderbaren Ansichten von Xuancheng", "artist": "Mei Qing"}, {"id": "CH-001319-0.Obj.RCH_1170e", "thumbnail": "/thumbnails/CH-001319-0.Obj.RCH_1170e.jpg", "title": "Der Tempel des westlichen Gipfels\r\nBlatt aus dem Album: Die wunderbaren Ansichten von Xuancheng", "artist": "Mei Qing"}, {"id": "CH-001319-0.Obj.RCH_1160", "thumbnail": "/thumbnails/CH-001319-0.Obj.RCH_1160.jpg", "title": "Landschaft", "artist": "Wang Yuanqi"}, {"id": "CH-001319-0.Obj.RCH_1170u", "thumbnail": "/thumbnails/CH-001319-0.Obj.RCH_1170u.jpg", "title": "In den Jade-Bergen\r\nBlatt aus dem Album: Die wunderbaren Ansichten von Xuancheng", "artist": "Mei Qing"}, {"id": "CH-001319-0.Obj.RCH_1170b", "thumbnail": "/thumbnails/CH-001319-0.Obj.RCH_1170b.jpg", "title": "Der Pass \u00fcber die Bojian-Berge\r\nBlatt aus dem Album: Die wunderbaren Ansichten von Xuancheng", "artist": "Mei Qing"}, {"id": "CH-001319-0.Obj.RCH_1170o", "thumbnail": "/thumbnails/CH-001319-0.Obj.RCH_1170o.jpg", "title": "Der Pavillon der Himmelspfeiler\r\nBlatt aus dem Album: Die wunderbaren Ansichten von Xuancheng", "artist": "Mei Qing"}, {"id": "CH-001319-0.Obj.RCH_1170m", "thumbnail": "/thumbnails/CH-001319-0.Obj.RCH_1170m.jpg", "title": "Unter den Weiden an der Furt des Ju- und Wan-Flusses\r\nBlatt aus dem Album: Die wunderbaren Ansichten von Xuancheng", "artist": "Mei Qing"}, {"id": "CH-001319-0.Obj.RCH_1170h", "thumbnail": "/thumbnails/CH-001319-0.Obj.RCH_1170h.jpg", "title": "Blick hinunter ins Gelbe Tal\r\nBlatt aus dem Album: Die wunderbaren Ansichten von Xuancheng", "artist": "Mei Qing"}, {"id": "CH-001319-0.Obj.RCH_1170i", "thumbnail": "/thumbnails/CH-001319-0.Obj.RCH_1170i.jpg", "title": "Gipfel \u00fcber den Wolken im Huayang-Gebirge\r\nBlatt aus dem Album: Die wunderbaren Ansichten von Xuancheng", "artist": "Mei Qing"}, {"id": "CH-001319-0.Obj.RCH_1170k", "thumbnail": "/thumbnails/CH-001319-0.Obj.RCH_1170k.jpg", "title": "Friedliches Dorf zwischen Lumo-Fluss und Xintian-Bergen\r\nBlatt aus dem Album: Die wunderbaren Ansichten von Xuancheng", "artist": "Mei Qing"}, {"id": "CH-001319-0.Obj.RCH_1170j", "thumbnail": "/thumbnails/CH-001319-0.Obj.RCH_1170j.jpg", "title": "Der Pavillon des Pflaumenbl\u00fctenschauens\r\nBlatt aus dem Album: Die wunderbaren Ansichten von Xuancheng", "artist": "Mei Qing"}, {"id": "CH-001319-0.Obj.RCH_1180a", "thumbnail": "/thumbnails/CH-001319-0.Obj.RCH_1180a.jpg", "title": "Fr\u00fchlingsberge\r\nAus dem Album: Landschaften nach grossen Meistern", "artist": "Dai Xi"}, {"id": "CH-001319-0.Obj.RCH_1137", "thumbnail": "/thumbnails/CH-001319-0.Obj.RCH_1137.jpg", "title": "Reisende in den Bergen", "artist": "Chen Guan"}, {"id": "CH-001319-0.Obj.RCH_1180j", "thumbnail": "/thumbnails/CH-001319-0.Obj.RCH_1180j.jpg", "title": "Aufklarender Himmel nach dem Schnee\r\nAus dem Album: Landschaften nach grossen Meistern", "artist": "Dai Xi"}, {"id": "CH-001319-0.Obj.RCH_1170g", "thumbnail": "/thumbnails/CH-001319-0.Obj.RCH_1170g.jpg", "title": "Die Regenbogen-Br\u00fccke in den Bojian-Bergen\r\nBlatt aus dem Album: Die wunderbaren Ansichten von Xuancheng", "artist": "Mei Qing"}, {"id": "CH-001319-0.Obj.RCH_1170p", "thumbnail": "/thumbnails/CH-001319-0.Obj.RCH_1170p.jpg", "title": "Auf der Terrasse des heimkehrenden Fr\u00fchlings\r\nBlatt aus dem Album: Die wunderbaren Ansichten von Xuancheng", "artist": "Mei Qing"}, {"id": "CH-001319-0.Obj.RCH_1170s", "thumbnail": "/thumbnails/CH-001319-0.Obj.RCH_1170s.jpg", "title": "Die Frische geniessen am Westlichen Wassergraben\r\nBlatt aus dem Album: Die wunderbaren Ansichten von Xuancheng", "artist": "Mei Qing"}, {"id": "CH-001319-0.Obj.RCH_1170r", "thumbnail": "/thumbnails/CH-001319-0.Obj.RCH_1170r.jpg", "title": "Die Halle des sich schl\u00e4ngelnden Flusses\r\nBlatt aus dem Album: Die wunderbaren Ansichten von Xuancheng", "artist": "Mei Qing"}, {"id": "CH-001319-0.Obj.RCH_1170w", "thumbnail": "/thumbnails/CH-001319-0.Obj.RCH_1170w.jpg", "title": "Auf der Suche nach den Unsterblichen in den Magu-Bergen\r\nBlatt aus dem Album: Die wunderbaren Ansichten von Xuancheng", "artist": "Mei Qing"}, {"id": "CH-001319-0.Obj.RCH_1170n", "thumbnail": "/thumbnails/CH-001319-0.Obj.RCH_1170n.jpg", "title": "Flussfahrt bei den Jingting-Bergen\r\nBlatt aus dem Album: Die wunderbaren Ansichten von Xuancheng", "artist": "Mei Qing"}, {"id": "CH-001319-0.Obj.RCH_1170x", "thumbnail": "/thumbnails/CH-001319-0.Obj.RCH_1170x.jpg", "title": "Entlang des Ost-Flusses\r\nBlatt aus dem Album: Die wunderbaren Ansichten von Xuancheng", "artist": "Mei Qing"}, {"id": "CH-001319-0.Obj.RCH_1170l", "thumbnail": "/thumbnails/CH-001319-0.Obj.RCH_1170l.jpg", "title": "Die Zwillings-Pagoden am Jingting-Gebirge\r\nBlatt aus dem Album: Die wunderbaren Ansichten von Xuancheng", "artist": "Mei Qing"}, {"id": "CH-001319-0.Obj.RCH_1182", "thumbnail": "/thumbnails/CH-001319-0.Obj.RCH_1182.jpg", "title": "Landschaft", "artist": "Sheng Maoye"}, {"id": "CH-001319-0.Obj.RCH_1175a", "thumbnail": "/thumbnails/CH-001319-0.Obj.RCH_1175a.jpg", "title": "\"Nach Hause zur\u00fcck\" von Tao Yuanming\nAus dem Album \"Landschaften nach Gedichten und Essays ber\u00fchmter Autoren\"", "artist": "Jin Nong"}, {"id": "CH-001319-0.Obj.RCH_1162e", "thumbnail": "/thumbnails/CH-001319-0.Obj.RCH_1162e.jpg", "title": "Strohgedeckte H\u00fctte unter B\u00e4umen\r\nAus dem Album: Landschaften im Stil von Song- und Yuan-Meistern", "artist": "Zhang Zongcang"}, {"id": "CH-001319-0.Obj.RCH_1142", "thumbnail": "/thumbnails/CH-001319-0.Obj.RCH_1142.jpg", "title": "Landschaft", "artist": "Chen Huan"}, {"id": "CH-001319-0.Obj.RCH_1162b", "thumbnail": "/thumbnails/CH-001319-0.Obj.RCH_1162b.jpg", "title": "Steile Klippen und weiter Fluss\r\nAus dem Album: Landschaften im Stil von Song- und Yuan-Meistern", "artist": "Zhang Zongcang"}, {"id": "CH-001319-0.Obj.RCH_1170v", "thumbnail": "/thumbnails/CH-001319-0.Obj.RCH_1170v.jpg", "title": "Nebel \u00fcber dem Qi-See\r\nBlatt aus dem Album: Die wunderbaren Ansichten von Xuancheng", "artist": "Mei Qing"}, {"id": "CH-001319-0.Obj.RCH_1228", "thumbnail": "/thumbnails/CH-001319-0.Obj.RCH_1228.jpg", "title": "Schwalbe und Aprikosenbl\u00fcte", "artist": "Lu Zhi"}, {"id": "CH-001319-0.Obj.RCH_1170t", "thumbnail": "/thumbnails/CH-001319-0.Obj.RCH_1170t.jpg", "title": "Ruhe und Einsamkeit am Ufer bei Wanzhi\r\nBlatt aus dem Album: Die wunderbaren Ansichten von Xuancheng", "artist": "Mei Qing"}, {"id": "CH-001319-0.Obj.RCH_1022", "thumbnail": "/thumbnails/CH-001319-0.Obj.RCH_1022.jpg", "title": "Unsterblicher, der Langlebigkeit vermittelt ", "artist": "Chen Hongshou "}, {"id": "CH-001319-0.Obj.RCH_1180b", "thumbnail": "/thumbnails/CH-001319-0.Obj.RCH_1180b.jpg", "title": "Wasserfall und einsame Kiefer\r\nAus dem Album: Landschaften nach grossen Meistern", "artist": "Dai Xi"}, {"id": "CH-001319-0.Obj.RCH_1162c", "thumbnail": "/thumbnails/CH-001319-0.Obj.RCH_1162c.jpg", "title": "Berge und Gipfel\r\nAus dem Album: Landschaften im Stil von Song- und Yuan-Meistern", "artist": "Zhang Zongcang"}, {"id": "CH-001319-0.Obj.RCH_1180d", "thumbnail": "/thumbnails/CH-001319-0.Obj.RCH_1180d.jpg", "title": "Bemalte Br\u00fccke und Weiden im Nebel\r\nAus dem Album: Landschaften nach grossen Meistern", "artist": "Dai Xi"}, {"id": "CH-001319-0.Obj.RCH_1180g", "thumbnail": "/thumbnails/CH-001319-0.Obj.RCH_1180g.jpg", "title": "Pavillon \u00fcber den Baumwipfeln\r\nAus dem Album: Landschaften nach grossen Meistern", "artist": "Dai Xi"}, {"id": "CH-001319-0.Obj.RCH_1177a", "thumbnail": "/thumbnails/CH-001319-0.Obj.RCH_1177a.jpg", "title": "Landschaft", "artist": "Qian Du"}, {"id": "CH-001319-0.Obj.RCH_1180h", "thumbnail": "/thumbnails/CH-001319-0.Obj.RCH_1180h.jpg", "title": "Hoher Pavillon in Nebel und Regen\r\nAus dem Album: Landschaften nach grossen Meistern", "artist": "Dai Xi"}, {"id": "CH-001319-0.Obj.RCH_1177b", "thumbnail": "/thumbnails/CH-001319-0.Obj.RCH_1177b.jpg", "title": "Landschaft", "artist": "Qian Du"}, {"id": "CH-001319-0.Obj.RCH_1172", "thumbnail": "/thumbnails/CH-001319-0.Obj.RCH_1172.jpg", "title": "Tausend Gipfel und zehntausend T\u00e4ler", "artist": "Gong Xian"}, {"id": "CH-001319-0.Obj.RCH_1229", "thumbnail": "/thumbnails/CH-001319-0.Obj.RCH_1229.jpg", "title": "Blumen und Fr\u00fcchte", "artist": "Xiang Yuanbian"}, {"id": "CH-001319-0.Obj.RCH_1150", "thumbnail": "/thumbnails/CH-001319-0.Obj.RCH_1150.jpg", "title": "Ein Gelehrter betrachtet einen Wasserfall", "artist": "Li Liufang"}, {"id": "CH-001319-0.Obj.RCH_1165b", "thumbnail": "/thumbnails/CH-001319-0.Obj.RCH_1165b.jpg", "title": "Fl\u00fcsschen am Bambushain\nAus \"Album mit Landschaften im Stil alter Meister\"", "artist": "Wang Jiu"}, {"id": "CH-001319-0.Obj.RCH_1236g", "thumbnail": "/thumbnails/CH-001319-0.Obj.RCH_1236g.jpg", "title": "Orchideen im Herbstwind", "artist": "Xu Fang"}, {"id": "CH-001319-0.Obj.RCH_1236f", "thumbnail": "/thumbnails/CH-001319-0.Obj.RCH_1236f.jpg", "title": "In einem buddhistischen Tempel am Westsee", "artist": "Wang Zhideng"}, {"id": "CH-001319-0.Obj.RCH_1165c", "thumbnail": "/thumbnails/CH-001319-0.Obj.RCH_1165c.jpg", "title": "Pavillon am Fluss\nAus \"Album mit Landschaften im Stil alter Meister\"", "artist": "Wang Jiu"}, {"id": "CH-001319-0.Obj.RCH_1145", "thumbnail": "/thumbnails/CH-001319-0.Obj.RCH_1145.jpg", "title": "Landschaft im Stil von Ni Zan", "artist": "Yun Xiang"}, {"id": "CH-001319-0.Obj.RCH_1151", "thumbnail": "/thumbnails/CH-001319-0.Obj.RCH_1151.jpg", "title": "Landschaft", "artist": "Li Liufang"}, {"id": "CH-001319-0.Obj.RCH_1153", "thumbnail": "/thumbnails/CH-001319-0.Obj.RCH_1153.jpg", "title": "Landschaft", "artist": "Mi Wangzhong"}, {"id": "CH-001319-0.Obj.RCH_1165a", "thumbnail": "/thumbnails/CH-001319-0.Obj.RCH_1165a.jpg", "title": "Tempel am Fluss\nAus \"Album mit Landschaften im Stil alter Meister\"", "artist": "Wang Jiu"}, {"id": "CH-001319-0.Obj.RCH_1236d", "thumbnail": "/thumbnails/CH-001319-0.Obj.RCH_1236d.jpg", "title": "Offener Pavillon in den Bergen", "artist": "Shen Zhou"}, {"id": "CH-001319-0.Obj.RCH_1236e", "thumbnail": "/thumbnails/CH-001319-0.Obj.RCH_1236e.jpg", "title": "F\u00fcr den Arzt Zhanyun", "artist": "Shen Shixing"}, {"id": "CH-001319-0.Obj.RCH_1156", "thumbnail": "/thumbnails/CH-001319-0.Obj.RCH_1156.jpg", "title": "Landschaft im Stil von Wang Meng", "artist": "Wu Li"}, {"id": "CH-001319-0.Obj.RCH_1236a", "thumbnail": "/thumbnails/CH-001319-0.Obj.RCH_1236a.jpg", "title": "Auf der Suche nach Pflaumenbl\u00fcten in den Bergen", "artist": "Chen Jiru"}, {"id": "CH-001319-0.Obj.RCH_1165d", "thumbnail": "/thumbnails/CH-001319-0.Obj.RCH_1165d.jpg", "title": "Einsamer Fischer\nAus \"Album mit Landschaften im Stil alter Meister\"", "artist": "Wang Jiu"}, {"id": "CH-001319-0.Obj.RCH_1165e", "thumbnail": "/thumbnails/CH-001319-0.Obj.RCH_1165e.jpg", "title": "Pavillon in den Wolken\nAus \"Album mit Landschaften im Stil alter Meister\"", "artist": "Wang Jiu"}, {"id": "CH-001319-0.Obj.RCH_1143", "thumbnail": "/thumbnails/CH-001319-0.Obj.RCH_1143.jpg", "title": "Der Berg Lingyan nach dem Schneefall", "artist": ""}, {"id": "CH-001319-0.Obj.RCH_1155", "thumbnail": "/thumbnails/CH-001319-0.Obj.RCH_1155.jpg", "title": "Landschaft im Stil von Huang Gongwang", "artist": "Lan Ying"}, {"id": "CH-001319-0.Obj.RCH_1141", "thumbnail": "/thumbnails/CH-001319-0.Obj.RCH_1141.jpg", "title": "Flusslandschaft", "artist": "Dong Qichang"}, {"id": "CH-001319-0.Obj.RCH_1236b", "thumbnail": "/thumbnails/CH-001319-0.Obj.RCH_1236b.jpg", "title": "Einsames Wirtshaus am Flussufer", "artist": "Xu Lin"}, {"id": "CH-001319-0.Obj.RCH_1165g", "thumbnail": "/thumbnails/CH-001319-0.Obj.RCH_1165g.jpg", "title": "In den Bergen versteckter Tempel\nAus \"Album mit Landschaften im Stil alter Meister\"", "artist": "Wang Jiu"}, {"id": "CH-001319-0.Obj.RCH_1021", "thumbnail": "/thumbnails/CH-001319-0.Obj.RCH_1021.jpg", "title": "Bodhidharma u\u0308berquert den Yangzi-Fluss auf einem Schilfgras", "artist": "Ding Yunpeng"}, {"id": "CH-001319-0.Obj.RCH_1165f", "thumbnail": "/thumbnails/CH-001319-0.Obj.RCH_1165f.jpg", "title": "Kahle B\u00e4ume im Schnee\nAus \"Album mit Landschaften im Stil alter Meister\"", "artist": "Wang Jiu"}, {"id": "CH-001319-0.Obj.RCH_1236c", "thumbnail": "/thumbnails/CH-001319-0.Obj.RCH_1236c.jpg", "title": "In den Lu-Bergen einen Freund zum Abschied begleiten", "artist": "Dong Qichang"}, {"id": "CH-001319-0.Obj.RCH_1154", "thumbnail": "/thumbnails/CH-001319-0.Obj.RCH_1154.jpg", "title": "Landschaft", "artist": "Zhang Ruitu"}, {"id": "CH-001319-0.Obj.RCH_1133", "thumbnail": "/thumbnails/CH-001319-0.Obj.RCH_1133.jpg", "title": "Landschaft", "artist": "Lu Zhi"}, {"id": "CH-001319-0.Obj.RCH_1136h", "thumbnail": "/thumbnails/CH-001319-0.Obj.RCH_1136h.jpg", "title": "Wasserfall und zwei V\u00f6gel\r\nAus dem Album \"Landschaften, Blumen und V\u00f6gel nach Song-K\u00fcnstlern\"", "artist": "K\u00fcnstler der Wu-Schule"}, {"id": "CH-001319-0.Obj.RCH_1180c", "thumbnail": "/thumbnails/CH-001319-0.Obj.RCH_1180c.jpg", "title": "Pavillon beim Wasser\r\nAus dem Album: Landschaften nach grossen Meistern", "artist": "Dai Xi"}, {"id": "CH-001319-0.Obj.RCH_1162d", "thumbnail": "/thumbnails/CH-001319-0.Obj.RCH_1162d.jpg", "title": "Kleine H\u00fctten am See\r\nAus dem Album: Landschaften im Stil von Song- und Yuan-Meistern", "artist": "Zhang Zongcang"}, {"id": "CH-001319-0.Obj.RCH_1175b", "thumbnail": "/thumbnails/CH-001319-0.Obj.RCH_1175b.jpg", "title": "\"Der Pavillon des Prinzen von Teng\" von Wang Bo\nAus dem Album \"Landschaften nach Gedichten und Essays ber\u00fchmter Autoren\"", "artist": "Jin Nong"}, {"id": "CH-001319-0.Obj.RCH_1162f", "thumbnail": "/thumbnails/CH-001319-0.Obj.RCH_1162f.jpg", "title": "Kiefern am Gebirgsbach\r\nAus dem Album: Landschaften im Stil von Song- und Yuan-Meistern", "artist": "Zhang Zongcang"}, {"id": "CH-001319-0.Obj.RCH_1162g", "thumbnail": "/thumbnails/CH-001319-0.Obj.RCH_1162g.jpg", "title": "Einsamer Wanderer in nebelverhangener Landschaft\r\nAus dem Album: Landschaften im Stil von Song- und Yuan-Meistern", "artist": "Zhang Zongcang"}, {"id": "CH-001319-0.Obj.RCH_1175c", "thumbnail": "/thumbnails/CH-001319-0.Obj.RCH_1175c.jpg", "title": "\"Die Lautenspielerin\" von Bai Juyi (772-846)\nAus dem Album \"Landschaften nach Gedichten und Essays ber\u00fchmter Autoren\"", "artist": "Jin Nong"}, {"id": "CH-001319-0.Obj.RCH_1135", "thumbnail": "/thumbnails/CH-001319-0.Obj.RCH_1135.jpg", "title": "Landschaft", "artist": "Tang Yin"}, {"id": "CH-001319-0.Obj.RCH_1175g", "thumbnail": "/thumbnails/CH-001319-0.Obj.RCH_1175g.jpg", "title": "\"Fahrt zur Roten Wand\" von Su Shi (1037-1101)\nAus dem Album \"Landschaften nach Gedichten und Essays ber\u00fchmter Autoren\"", "artist": "Jin Nong"}, {"id": "CH-001319-0.Obj.RCH_1180e", "thumbnail": "/thumbnails/CH-001319-0.Obj.RCH_1180e.jpg", "title": "Mit einem Kranich die Kiefern besuchen\r\nAus dem Album: Landschaften nach grossen Meistern", "artist": "Dai Xi"}, {"id": "CH-001319-0.Obj.RCH_1175f", "thumbnail": "/thumbnails/CH-001319-0.Obj.RCH_1175f.jpg", "title": "\"Der Pavillon des trunkenen Alten\" von Ouyang Xiu (1007-1072)\nAus dem Album \"Landschaften nach Gedichten und Essays ber\u00fchmter Autoren\"", "artist": "Jin Nong"}, {"id": "CH-001319-0.Obj.RCH_1176h", "thumbnail": "/thumbnails/CH-001319-0.Obj.RCH_1176h.jpg", "title": "Landschaft\r\nAus einem Album mit Landschaften, montiert als zwei Querrollen", "artist": "Huang Shen"}, {"id": "CH-001319-0.Obj.RCH_1175d", "thumbnail": "/thumbnails/CH-001319-0.Obj.RCH_1175d.jpg", "title": "\"Die Bambus-Pavillons von Huanggang\" von Wang Yucheng (954-1001)\nAus dem Album \"Landschaften nach Gedichten und Essays ber\u00fchmter Autoren\"", "artist": "Jin Nong"}, {"id": "CH-001319-0.Obj.RCH_1180f", "thumbnail": "/thumbnails/CH-001319-0.Obj.RCH_1180f.jpg", "title": "Herbst am Berg Wu\r\nAus dem Album: Landschaften nach grossen Meistern", "artist": "Dai Xi"}, {"id": "CH-001319-0.Obj.RCH_1175e", "thumbnail": "/thumbnails/CH-001319-0.Obj.RCH_1175e.jpg", "title": "\"Der H\u00fcgel westlich des Pl\u00e4tteisen-Teiches\" von Liu Zongyuan (773-819)\nAus dem Album \"Landschaften nach Gedichten und Essays ber\u00fchmter Autoren\"", "artist": "Jin Nong"}, {"id": "CH-001319-0.Obj.RCH_1176i", "thumbnail": "/thumbnails/CH-001319-0.Obj.RCH_1176i.jpg", "title": "Landschaft\r\nAus einem Album mit Landschaften, montiert als zwei Querrollen", "artist": "Huang Shen"}, {"id": "CH-001319-0.Obj.RCH_1023", "thumbnail": "/thumbnails/CH-001319-0.Obj.RCH_1023.jpg", "title": "Die Vier Freuden des Nan Shenglu\n", "artist": "Chen Hongshou "}, {"id": "CH-001319-0.Obj.RCH_1176d", "thumbnail": "/thumbnails/CH-001319-0.Obj.RCH_1176d.jpg", "title": "Landschaft\r\nAus einem Album mit Landschaften, montiert als zwei Querrollen", "artist": "Huang Shen"}, {"id": "CH-001319-0.Obj.RCH_1175h", "thumbnail": "/thumbnails/CH-001319-0.Obj.RCH_1175h.jpg", "title": "\"Elegie \u00fcber den Klang des Herbstes\" von Ouyang Xiu (1007-1072)\nAus dem Album \"Landschaften nach Gedichten und Essays ber\u00fchmter Autoren\"", "artist": "Jin Nong"}, {"id": "CH-001319-0.Obj.RCH_1136a", "thumbnail": "/thumbnails/CH-001319-0.Obj.RCH_1136a.jpg", "title": "F\u00fcnf Enten\r\nAus dem Album \"Landschaften, Blumen und V\u00f6gel nach Song-K\u00fcnstlern\"", "artist": "K\u00fcnstler der Wu-Schule"}, {"id": "CH-001319-0.Obj.RCH_1175i", "thumbnail": "/thumbnails/CH-001319-0.Obj.RCH_1175i.jpg", "title": "\"Der Pavillon der Kraniche\" von Su Shi (1037-1101)\nAus dem Album \"Landschaften nach Gedichten und Essays ber\u00fchmter Autoren\"", "artist": "Jin Nong"}, {"id": "CH-001319-0.Obj.RCH_1176e", "thumbnail": "/thumbnails/CH-001319-0.Obj.RCH_1176e.jpg", "title": "Landschaft\r\nAus einem Album mit Landschaften, montiert als zwei Querrollen", "artist": "Huang Shen"}, {"id": "CH-001319-0.Obj.RCH_1139", "thumbnail": "/thumbnails/CH-001319-0.Obj.RCH_1139.jpg", "title": "Landschaft im Stil von Dong Yuan", "artist": "Dong Qichang"}, {"id": "CH-001319-0.Obj.RCH_1176g", "thumbnail": "/thumbnails/CH-001319-0.Obj.RCH_1176g.jpg", "title": "Landschaft\r\nAus einem Album mit Landschaften, montiert als zwei Querrollen", "artist": "Huang Shen"}, {"id": "CH-001319-0.Obj.RCH_1175k", "thumbnail": "/thumbnails/CH-001319-0.Obj.RCH_1175k.jpg", "title": "Tempel am Fluss\nAus dem Album \"Landschaften nach Gedichten und Essays ber\u00fchmter Autoren\"", "artist": "Jin Nong"}, {"id": "CH-001319-0.Obj.RCH_1136c", "thumbnail": "/thumbnails/CH-001319-0.Obj.RCH_1136c.jpg", "title": "G\u00e4nseschwarm\r\nAus dem Album \"Landschaften, Blumen und V\u00f6gel nach Song-K\u00fcnstlern\"", "artist": "K\u00fcnstler der Wu-Schule"}, {"id": "CH-001319-0.Obj.RCH_1136b", "thumbnail": "/thumbnails/CH-001319-0.Obj.RCH_1136b.jpg", "title": "Gelehrter, der den Wolken nachsieht\r\nAus dem Album \"Landschaften, Blumen und V\u00f6gel nach Song-K\u00fcnstlern\"", "artist": "K\u00fcnstler der Wu-Schule"}, {"id": "CH-001319-0.Obj.RCH_1180i", "thumbnail": "/thumbnails/CH-001319-0.Obj.RCH_1180i.jpg", "title": "Herbststimmung am Wasser\r\nAus dem Album: Landschaften nach grossen Meistern", "artist": "Dai Xi"}, {"id": "CH-001319-0.Obj.RCH_1175j", "thumbnail": "/thumbnails/CH-001319-0.Obj.RCH_1175j.jpg", "title": "\"Der Pavillon zum Betrachten des Flusses\" von Song Lian\r\nAus dem Album: Gedichte und Essays ber\u00fchmter Schriftsteller", "artist": "Jin Nong"}, {"id": "CH-001319-0.Obj.RCH_1176f", "thumbnail": "/thumbnails/CH-001319-0.Obj.RCH_1176f.jpg", "title": "Landschaft\r\nAus einem Album mit Landschaften, montiert als zwei Querrollen", "artist": "Huang Shen"}, {"id": "CH-001319-0.Obj.RCH_1138", "thumbnail": "/thumbnails/CH-001319-0.Obj.RCH_1138.jpg", "title": "Gelehrter beim Betrachten eines Wasserfalls", "artist": "Chen Guan"}, {"id": "CH-001319-0.Obj.RCH_1136f", "thumbnail": "/thumbnails/CH-001319-0.Obj.RCH_1136f.jpg", "title": "Landschaft in Anlehnung an den Xiao- und Xiang-Fluss von Muqi\r\nAus dem Album \"Landschaften, Blumen und V\u00f6gel nach Song-K\u00fcnstlern\"", "artist": "K\u00fcnstler der Wu-Schule"}, {"id": "CH-001319-0.Obj.RCH_1136g", "thumbnail": "/thumbnails/CH-001319-0.Obj.RCH_1136g.jpg", "title": "Vogel auf Felsen\r\nAus dem Album \"Landschaften, Blumen und V\u00f6gel nach Song-K\u00fcnstlern\"", "artist": "K\u00fcnstler der Wu-Schule"}, {"id": "CH-001319-0.Obj.RCH_1176c", "thumbnail": "/thumbnails/CH-001319-0.Obj.RCH_1176c.jpg", "title": "Landschaft\r\nAus einem Album mit Landschaften, montiert als zwei Querrollen", "artist": "Huang Shen"}, {"id": "CH-001319-0.Obj.RCH_1176a", "thumbnail": "/thumbnails/CH-001319-0.Obj.RCH_1176a.jpg", "title": "Landschaft\r\nAus einem Album mit Landschaften, montiert als zwei Querrollen", "artist": "Huang Shen"}, {"id": "CH-001319-0.Obj.RCH_1136e", "thumbnail": "/thumbnails/CH-001319-0.Obj.RCH_1136e.jpg", "title": "Vogel auf einem Zweig\r\nAus dem Album \"Landschaften, Blumen und V\u00f6gel nach Song-K\u00fcnstlern\"", "artist": "K\u00fcnstler der Wu-Schule"}, {"id": "CH-001319-0.Obj.RCH_1136d", "thumbnail": "/thumbnails/CH-001319-0.Obj.RCH_1136d.jpg", "title": "Lanschaft im Stil von Xia Gui\r\nAus dem Album \"Landschaften, Blumen und V\u00f6gel nach Song-K\u00fcnstlern\"", "artist": "K\u00fcnstler der Wu-Schule"}, {"id": "CH-001319-0.Obj.RCH_1175l", "thumbnail": "/thumbnails/CH-001319-0.Obj.RCH_1175l.jpg", "title": "Tempelhalle in den Bergen\nAus dem Album \"Landschaften nach Gedichten und Essays ber\u00fchmter Autoren\"", "artist": "Jin Nong"}, {"id": "CH-001319-0.Obj.RCH_1159", "thumbnail": "/thumbnails/CH-001319-0.Obj.RCH_1159.jpg", "title": "Landschaft nach Dong Qichang im Stil von Ni Zan und Huang Gongwang", "artist": "Wang Yuanqi"}, {"id": "CH-001319-0.Obj.RCH_1020", "thumbnail": "/thumbnails/CH-001319-0.Obj.RCH_1020.jpg", "title": "Wo die Unsterblichen weilen am Ufer des Qi-Flusses", "artist": "Xie Shichen"}, {"id": "CH-001319-0.Obj.RCH_1158", "thumbnail": "/thumbnails/CH-001319-0.Obj.RCH_1158.jpg", "title": "Landschaft im Stil des Wu Zhen", "artist": "Wang Yuanqi"}, {"id": "CH-001319-0.Obj.RCH_1166", "thumbnail": "/thumbnails/CH-001319-0.Obj.RCH_1166.jpg", "title": "Landschaft", "artist": "Prinz Aisin Gioro Yongrong"}, {"id": "CH-001319-0.Obj.RCH_1165h", "thumbnail": "/thumbnails/CH-001319-0.Obj.RCH_1165h.jpg", "title": "Schneelandschaft\nAus \"Album mit Landschaften im Stil alter Meister\"", "artist": "Wang Jiu"}, {"id": "CH-001319-0.Obj.RCH_1163", "thumbnail": "/thumbnails/CH-001319-0.Obj.RCH_1163.jpg", "title": "Landschaft im Stil von Wu Zhen", "artist": "Wang Chen"}, {"id": "CH-001319-0.Obj.RCH_1236h", "thumbnail": "/thumbnails/CH-001319-0.Obj.RCH_1236h.jpg", "title": "Angesichts der Aufenthaltsorte der Unsterblichen", "artist": "Wang Chong"}, {"id": "CH-001319-0.Obj.RCH_1149", "thumbnail": "/thumbnails/CH-001319-0.Obj.RCH_1149.jpg", "title": "Nebel zieht in die Bergt\u00e4ler", "artist": "Mo Shilong"}]